setup.py
mezzaninetheme_moderna.egg-info/PKG-INFO
mezzaninetheme_moderna.egg-info/SOURCES.txt
mezzaninetheme_moderna.egg-info/dependency_links.txt
mezzaninetheme_moderna.egg-info/top_level.txt
moderna/__init__.py