Metadata-Version: 1.0
Name: mezzaninetheme-moderna
Version: 1.0
Summary: Mezzanine CMS themes: Moderna
Home-page: https://github.com/hirokiky/mezzaninetheme-moderna
Author: Hiroki Kiyohara
Author-email: hirokiky@gmail.com
License: MIT
Platform: UNKNOWN
